LibDOM/Attributes.py
LibDOM/Elements.py
LibDOM/Propertys.py
LibDOM-0.1.3.dist-info/LICENSE
LibDOM-0.1.3.dist-info/METADATA
LibDOM-0.1.3.dist-info/WHEEL
LibDOM-0.1.3.dist-info/top_level.txt
LibDOM-0.1.3.dist-info/RECORD
