Metadata-Version: 2.1
Name: LibDOM
Version: 0.1.3
Summary: LibDOM is a Python library that abstracts all modern HTML tags, enabling you to build dynamic HTML documents programmatically. With a clean and intuitive Framework, LibDOM simplifies web development by allowing you to generate and manipulate HTML entirely in Python. Perfect for creating dynamic, maintainable, and responsive web pages.
Home-page: https://github.com/PSalleSDev/LibDOM
Author: Pedro Salles
License: MIT License
Keywords: Html,Builder,Html Builder,DOM,Document Object Model,DOM Builder
License-File: LICENSE
